LICENSE
MANIFEST.in
README.md
setup.py
olympus/__init__.py
olympus/eval_report.py
olympus/eval_report_test.py
olympus/eval_task.py
olympus/eval_task_test.py
olympus/log.py
olympus/model.py
olympus/setting.py
olympus/utils.py
olympus_hitc.egg-info/PKG-INFO
olympus_hitc.egg-info/SOURCES.txt
olympus_hitc.egg-info/dependency_links.txt
olympus_hitc.egg-info/requires.txt
olympus_hitc.egg-info/top_level.txt