Metadata-Version: 1.0
Name: olympus-hitc
Version: 0.0.15
Summary: an api of project olympus
Home-page: http://gitlab.hobot.cc/ptd/ap/toolchain/ai-platform/olympus/tree/dev/python
Author: gaoyu
Author-email: v-yu.gao@horizon.ai
License: CMIT License
